LICENSE.txt
MANIFEST.in
README.md
setup.cfg
setup.py
django_grappelli_autocomplete_fk_edit_link.egg-info/PKG-INFO
django_grappelli_autocomplete_fk_edit_link.egg-info/SOURCES.txt
django_grappelli_autocomplete_fk_edit_link.egg-info/dependency_links.txt
django_grappelli_autocomplete_fk_edit_link.egg-info/requires.txt
django_grappelli_autocomplete_fk_edit_link.egg-info/top_level.txt
grappelli_autocomplete_fk_edit_link/__init__.py
grappelli_autocomplete_fk_edit_link/static/admin/js/autocomplete-fk-edit-link.js