Metadata-Version: 1.1
Name: django-grappelli-autocomplete-fk-edit-link
Version: 0.1.1
Summary: ModelAdmin mixin that adds edit links to Django Grappelli autocomplete lookups.
Home-page: https://github.com/CrossWaterBridge/django-grappelli-autocomplete-fk-edit-link
Author: UNKNOWN
Author-email: UNKNOWN
License: MIT
Download-URL: https://github.com/CrossWaterBridge/django-grappelli-autocomplete-fk-edit-link/tarball/0.1.0
Platform: UNKNOWN
